pykdgrav3_utils/__init__.py
pykdgrav3_utils/fofstat.py
pykdgrav3_utils/hdf5.py
pykdgrav3_utils/ic.py
pykdgrav3_utils/timings.py
pykdgrav3_utils/tipsy.py
pykdgrav3_utils/units.py
pykdgrav3_utils-0.1.1.dist-info/LICENSE
pykdgrav3_utils-0.1.1.dist-info/METADATA
pykdgrav3_utils-0.1.1.dist-info/WHEEL
pykdgrav3_utils-0.1.1.dist-info/RECORD
