Metadata-Version: 2.1
Name: pykdgrav3_utils
Version: 0.1.1
Summary: Utility packages for working with PKDGRAV3 outputs
Home-page: https://research.iac.es/proyecto/PKDGRAV3/
License: MIT
Author: Isaac Alonso Asensio
Author-email: isaac.alonso.asensio@iac.es
Requires-Python: >=3.8.1,<4.0.0
Classifier: License :: OSI Approved :: MIT License
Classifier: Programming Language :: Python :: 3
Classifier: Programming Language :: Python :: 3.9
Classifier: Programming Language :: Python :: 3.10
Classifier: Programming Language :: Python :: 3.11
Classifier: Programming Language :: Python :: 3.12
Requires-Dist: h5py (>=3.8.0)
Requires-Dist: matplotlib (>3.7.1)
Requires-Dist: numpy (>=1.24.4,<2.0.0)
Project-URL: Repository, https://bitbucket.org/iacsimgro/pykdgrav3_utils
